tandems/HELP
tandems/__init__.py
tandems/data/AM1_5 smarts295.ext.txt
tandems/data/AM1_5 smarts295.out.txt
tandems/data/lat40.clusters.npy
tandems/data/lat40.timePerCluster.npy
tandems-0.989.dist-info/LICENSE
tandems-0.989.dist-info/METADATA
tandems-0.989.dist-info/WHEEL
tandems-0.989.dist-info/top_level.txt
tandems-0.989.dist-info/RECORD
