Metadata-Version: 2.1
Name: tandems
Version: 0.989
Summary: Calculates multijunction solar cell efficiency
Home-page: https://github.com/Ripalda/Tandems
Author: Jose M. Ripalda
Author-email: j.ripalda@csic.es
License: UNKNOWN
Project-URL: Bug Tracker, https://github.com/Ripalda/Tandems/issues
Platform: UNKNOWN
Classifier: Programming Language :: Python :: 3
Classifier: License :: OSI Approved :: GNU General Public License (GPL)
Classifier: Operating System :: OS Independent
Requires-Python: >=3.6
License-File: LICENSE
Requires-Dist: numpy
Requires-Dist: matplotlib
Requires-Dist: scipy
Requires-Dist: sklearn
Requires-Dist: datetime
